<?xml version='1.0' encoding='UTF-8'?>
<song xmlns="http://openlyrics.info/namespace/2009/song" version="0.8" createdIn="OpenLP 2.4" modifiedIn="OpenLP 2.4" modifiedDate="2016-03-26T20:24:54">
  <properties>
    <titles>
      <title>പോകുന്നു ഞാനിന്ന് യേശുവിന്നായ്</title>
    </titles>
    <verseOrder>v1 v2 v1 v3 v1 v4 v1 v5 v1 v6 v1</verseOrder>
    <authors>
      <author>Author Unknown</author>
    </authors>
  </properties>
  <lyrics>
    <verse name="v1">
      <lines>പോകുന്നു ഞാനിന്ന് യേശുവിന്നായ്<br/>പോകുന്നു ക്രൂശിന്റെ പോരാളിയായ്</lines>
    </verse>
    <verse name="v2">
      <lines>നിന്ദകൾ പീഡകൾ വേദനവേളകൾ<br/>വന്നാലും ക്ഷീണനായ് തീരാതെ പാരിൽ</lines>
    </verse>
    <verse name="v3">
      <lines>വിളിച്ചവൻ വിശ്വസ്തൻ മാറാത്ത വല്ലഭൻ<br/>വിശ്വാസനായകൻ യേശുവെ നോക്കി ഞാൻ</lines>
    </verse>
    <verse name="v4">
      <lines>ആകലനേരത്തിൽ ആവശ്യഭാരത്തിൽ<br/>ആശ്വാസദായകനാണെന്റെ നായകൻ</lines>
    </verse>
    <verse name="v5">
      <lines>വേണ്ടെനിക്കീലോകമഹിമകളൊന്നുമേ<br/>വേണ്ടതെല്ലാമുണ്ടീ ക്രിസ്തുവിലെന്നുമേ</lines>
    </verse>
    <verse name="v6">
      <lines>ഒട്ടും പിൻമാറാതെ ഓട്ടം ഞാനോടിടും<br/>ഒടുവിലെൻ വീട്ടിൽ ഞാൻ വിശ്രമം നേടിടും.</lines>
    </verse>
  </lyrics>
</song>
